{"data":{"markdownRemark":{"htmlAst":{"type":"root","children":[{"type":"element","tagName":"h1","properties":{},"children":[{"type":"text","value":"Jumbo CLI"}]},{"type":"text","value":"\n"},{"type":"element","tagName":"p","properties":{},"children":[{"type":"text","value":"In this section you will find all the commands available in the Jumbo CLI to manipulate:"}]},{"type":"text","value":"\n"},{"type":"element","tagName":"ul","properties":{},"children":[{"type":"text","value":"\n"},{"type":"element","tagName":"li","properties":{},"children":[{"type":"element","tagName":"a","properties":{"href":"/docs/commands/cluster"},"children":[{"type":"text","value":"clusters"}]}]},{"type":"text","value":"\n"},{"type":"element","tagName":"li","properties":{},"children":[{"type":"element","tagName":"a","properties":{"href":"/docs/commands/node"},"children":[{"type":"text","value":"nodes"}]}]},{"type":"text","value":"\n"},{"type":"element","tagName":"li","properties":{},"children":[{"type":"element","tagName":"a","properties":{"href":"/docs/commands/service"},"children":[{"type":"text","value":"services"}]}]},{"type":"text","value":"\n"},{"type":"element","tagName":"li","properties":{},"children":[{"type":"element","tagName":"a","properties":{"href":"/docs/commands/component"},"children":[{"type":"text","value":"components"}]}]},{"type":"text","value":"\n"}]},{"type":"text","value":"\n"},{"type":"element","tagName":"p","properties":{},"children":[{"type":"text","value":"There are two ways of using the CLI:"}]},{"type":"text","value":"\n"},{"type":"element","tagName":"ul","properties":{},"children":[{"type":"text","value":"\n"},{"type":"element","tagName":"li","properties":{},"children":[{"type":"text","value":"By typing each command individually with "},{"type":"element","tagName":"code","properties":{"className":["language-text"]},"children":[{"type":"text","value":"jumbo <command>"}]},{"type":"text","value":" in your terminal;"}]},{"type":"text","value":"\n"},{"type":"element","tagName":"li","properties":{},"children":[{"type":"text","value":"By entering the Jumbo shell."}]},{"type":"text","value":"\n"}]},{"type":"text","value":"\n"},{"type":"element","tagName":"p","properties":{},"children":[{"type":"text","value":"We recommand using the shell, because it makes commands lighter and optimizes data loading. However it is sometimes not possible to enter a shell (e.g. in bash scripts)."}]},{"type":"text","value":"\n"},{"type":"element","tagName":"h2","properties":{},"children":[{"type":"text","value":"Using the Jumbo shell"}]},{"type":"text","value":"\n"},{"type":"element","tagName":"p","properties":{},"children":[{"type":"text","value":"You can enter the jumbo shell with the command "},{"type":"element","tagName":"code","properties":{"className":["language-text"]},"children":[{"type":"text","value":"jumbo"}]},{"type":"text","value":". The principal advantage of the shell is that it allows to set the "},{"type":"element","tagName":"strong","properties":{},"children":[{"type":"text","value":"Jumbo context"}]},{"type":"text","value":" to a sepcific cluster."},{"type":"element","tagName":"br","properties":{},"children":[]},{"type":"text","value":"\nOnce the context is set to a cluster, all the commands will be applied to that cluster without having to specify it with the "},{"type":"element","tagName":"code","properties":{"className":["language-text"]},"children":[{"type":"text","value":"--cluster"}]},{"type":"text","value":" tag."}]},{"type":"text","value":"\n"},{"type":"element","tagName":"h2","properties":{},"children":[{"type":"text","value":"Not using the Jumbo shell"}]},{"type":"text","value":"\n"},{"type":"element","tagName":"p","properties":{},"children":[{"type":"text","value":"In this case, it is not possible to set a context. For every node or service command, it is necessary to specify the cluster with the tag "},{"type":"element","tagName":"code","properties":{"className":["language-text"]},"children":[{"type":"text","value":"--cluster"}]},{"type":"text","value":"."}]}],"data":{"quirksMode":false}},"id":"059554ac-0672-5099-be36-896e5ef836c0","frontmatter":{"title":"Jumbo CLI"}},"allMarkdownRemark":{"edges":[{"node":{"id":"e1db4b56-399c-5ce9-b4f3-44e35c15e979","frontmatter":{"title":"Overview","sort":1},"fields":{"slug":"docs"}}},{"node":{"id":"18de8870-8bdb-55c0-bb08-f34743a5bd02","frontmatter":{"title":"Getting started","sort":2},"fields":{"slug":"docs/getting-started"}}},{"node":{"id":"60177a56-5098-56bc-ad8c-1c8e09e6db7d","frontmatter":{"title":"Key principles","sort":2},"fields":{"slug":"docs/getting-started/key-principles"}}},{"node":{"id":"aa63ec29-6814-5475-b429-b44f8a3a321a","frontmatter":{"title":"Cluster commands","sort":2},"fields":{"slug":"docs/commands/cluster"}}},{"node":{"id":"059554ac-0672-5099-be36-896e5ef836c0","frontmatter":{"title":"Jumbo CLI","sort":3},"fields":{"slug":"docs/commands"}}},{"node":{"id":"e6f673ea-b3ef-5222-9873-81fde69f5c67","frontmatter":{"title":"Installation","sort":3},"fields":{"slug":"docs/getting-started/installation"}}},{"node":{"id":"5c0f544c-210b-53b3-aced-d8fc1ef74133","frontmatter":{"title":"Node commands","sort":3},"fields":{"slug":"docs/commands/node"}}},{"node":{"id":"c472559c-4c09-5b40-a73e-282542bc5086","frontmatter":{"title":"Advanced usage","sort":4},"fields":{"slug":"docs/advanced-usage"}}},{"node":{"id":"96aaf1ee-6a7d-579e-b7b9-243a7b0efba3","frontmatter":{"title":"Cluster configuration","sort":4},"fields":{"slug":"docs/getting-started/configuration"}}},{"node":{"id":"18cdb0a5-14a7-548c-a524-bdfef3dc6c52","frontmatter":{"title":"Service commands","sort":4},"fields":{"slug":"docs/commands/service"}}},{"node":{"id":"da2f734a-95f7-519e-bc1c-206d3632ad21","frontmatter":{"title":"Supported services and components","sort":5},"fields":{"slug":"docs/supported"}}},{"node":{"id":"cfd8df8a-f582-51f6-93bf-69f51079fe37","frontmatter":{"title":"Component commands","sort":5},"fields":{"slug":"docs/commands/component"}}},{"node":{"id":"61964963-bd57-51de-8091-cb0f298dd252","frontmatter":{"title":"Cluster provisioning","sort":5},"fields":{"slug":"docs/getting-started/provisioning"}}},{"node":{"id":"8f1f362b-9af8-5d51-adae-d73f07d1d1fc","frontmatter":{"title":"Versions","sort":6},"fields":{"slug":"docs/versions"}}}]},"site":{"siteMetadata":{"version":"0.4.4"}}},"pageContext":{"slug":"docs/commands"}}